mir/xdg/__init__.py
mir.xdg-1.0.0.dist-info/DESCRIPTION.rst
mir.xdg-1.0.0.dist-info/METADATA
mir.xdg-1.0.0.dist-info/RECORD
mir.xdg-1.0.0.dist-info/WHEEL
mir.xdg-1.0.0.dist-info/metadata.json
mir.xdg-1.0.0.dist-info/top_level.txt
