Metadata-Version: 2.0
Name: mir.xdg
Version: 1.0.0
Summary: XDG Base Directory support
Home-page: https://github.com/darkfeline/mir.xdg
Author: Allen Li
Author-email: darkfeline@felesatra.moe
License: UNKNOWN
Platform: UNKNOWN
Classifier: Development Status :: 5 - Production/Stable
Classifier: Intended Audience :: Developers
Classifier: License :: OSI Approved :: Apache Software License
Classifier: Programming Language :: Python :: 3.6
Requires-Python: ~=3.6
